biopipen/__init__.py
biopipen/core/__init__.py
biopipen/core/config.py
biopipen/core/config.toml
biopipen/core/defaults.py
biopipen/core/filters.py
biopipen/core/proc.py
biopipen/core/testing.py
biopipen/ns/__init__.py
biopipen/ns/bam.py
biopipen/ns/bed.py
biopipen/ns/cellranger.py
biopipen/ns/cellranger_pipeline.py
biopipen/ns/cnv.py
biopipen/ns/cnvkit.py
biopipen/ns/cnvkit_pipeline.py
biopipen/ns/delim.py
biopipen/ns/gene.py
biopipen/ns/gsea.py
biopipen/ns/misc.py
biopipen/ns/plot.py
biopipen/ns/protein.py
biopipen/ns/regulatory.py
biopipen/ns/rnaseq.py
biopipen/ns/scrna.py
biopipen/ns/scrna_metabolic_landscape.py
biopipen/ns/snp.py
biopipen/ns/stats.py
biopipen/ns/tcgamaf.py
biopipen/ns/tcr.py
biopipen/ns/vcf.py
biopipen/ns/web.py
biopipen/reports/bam/CNAClinic.svelte
biopipen/reports/bam/CNVpytor.svelte
biopipen/reports/bam/ControlFREEC.svelte
biopipen/reports/cellranger/CellRangerCount.svelte
biopipen/reports/cellranger/CellRangerSummary.svelte
biopipen/reports/cellranger/CellRangerVdj.svelte
biopipen/reports/cnv/AneuploidyScore.svelte
biopipen/reports/cnv/AneuploidyScoreSummary.svelte
biopipen/reports/cnv/TMADScoreSummary.svelte
biopipen/reports/cnvkit/CNVkitDiagram.svelte
biopipen/reports/cnvkit/CNVkitHeatmap.svelte
biopipen/reports/cnvkit/CNVkitScatter.svelte
biopipen/reports/common.svelte
biopipen/reports/gsea/FGSEA.svelte
biopipen/reports/gsea/GSEA.svelte
biopipen/reports/protein/ProdigySummary.svelte
biopipen/reports/scrna/CellsDistribution.svelte
biopipen/reports/scrna/DimPlots.svelte
biopipen/reports/scrna/MQuad.svelte
biopipen/reports/scrna/MarkersFinder.svelte
biopipen/reports/scrna/MetaMarkers.svelte
biopipen/reports/scrna/RadarPlots.svelte
biopipen/reports/scrna/VireoSNP.svelte
biopipen/reports/scrna_metabolic_landscape/MetabolicFeatures.svelte
biopipen/reports/scrna_metabolic_landscape/MetabolicPathwayActivity.svelte
biopipen/reports/scrna_metabolic_landscape/MetabolicPathwayHeterogeneity.svelte
biopipen/reports/snp/PlinkCallRate.svelte
biopipen-1.1.10.dist-info/METADATA
biopipen-1.1.10.dist-info/WHEEL
biopipen-1.1.10.dist-info/entry_points.txt
biopipen-1.1.10.dist-info/RECORD
