Metadata-Version: 2.4
Name: biopipen
Version: 1.1.10
Summary: Bioinformatics processes/pipelines that can be run from `pipen run`
License: MIT
Author: pwwang
Author-email: pwwang@pwwang.com
Requires-Python: >=3.9,<4.0
Classifier: License :: OSI Approved :: MIT License
Classifier: Programming Language :: Python :: 3
Classifier: Programming Language :: Python :: 3.9
Classifier: Programming Language :: Python :: 3.10
Classifier: Programming Language :: Python :: 3.11
Classifier: Programming Language :: Python :: 3.12
Classifier: Programming Language :: Python :: 3.13
Classifier: Programming Language :: Python :: 3.14
Provides-Extra: log2file
Provides-Extra: runinfo
Requires-Dist: datar[pandas] (>=0.15.8,<0.16.0)
Requires-Dist: pipen-board[report] (>=1.1,<2.0)
Requires-Dist: pipen-cli-run (>=1.0,<2.0)
Requires-Dist: pipen-deprecated (>=1.0,<2.0)
Requires-Dist: pipen-filters (>=1.1.2,<2.0.0)
Requires-Dist: pipen-log2file (>=1.1,<2.0) ; extra == "log2file"
Requires-Dist: pipen-poplog (>=1.1,<2.0)
Requires-Dist: pipen-runinfo (>=1.1,<2.0) ; extra == "runinfo"
Requires-Dist: pipen-verbose (>=1.1,<2.0)
